README.md
setup.py
hafer.egg-info/PKG-INFO
hafer.egg-info/SOURCES.txt
hafer.egg-info/dependency_links.txt
hafer.egg-info/not-zip-safe
hafer.egg-info/requires.txt
hafer.egg-info/top_level.txt
haferml/__init__.py
haferml/version.py
haferml/data/__init__.py
haferml/data/analysis/__init__.py
haferml/data/analysis/descriptions.py
haferml/data/wrangling/__init__.py
haferml/data/wrangling/datetime.py
haferml/data/wrangling/json.py
haferml/data/wrangling/misc.py
haferml/etl/__init__.py
haferml/etl/extract/__init__.py
haferml/etl/transform/__init__.py
haferml/etl/transform/pipeline.py
haferml/lab/__init__.py
haferml/lab/data/__init__.py
haferml/lab/data/extraction/__init__.py
haferml/lab/data/extraction/sql.py
haferml/preprocess/__init__.py
haferml/preprocess/ingredients.py
haferml/preprocess/pipeline.py
haferml/sync/__init__.py
haferml/sync/aws.py
haferml/sync/local.py
haferml/texts/__init__.py
haferml/texts/validator.py
haferml/texts/words.py
haferml/texts/wrangling/__init__.py
haferml/texts/wrangling/companies.py
haferml/texts/wrangling/consts.py
haferml/utils/__init__.py
haferml/utils/sugar.py